audittrail/__init__.py
audittrail/anomaly.py
audittrail/auth.py
audittrail/cli.py
audittrail/compliance_report.py
audittrail/key_manager.py
audittrail/ledger.py
audittrail/middleware.py
audittrail/signatures.py
audittrail/timestamp.py
audittrail/worm.py
audittrail-1.0.1.dist-info/licenses/LICENSE
audittrail-1.0.1.dist-info/METADATA
audittrail-1.0.1.dist-info/WHEEL
audittrail-1.0.1.dist-info/entry_points.txt
audittrail-1.0.1.dist-info/top_level.txt
audittrail-1.0.1.dist-info/RECORD
