Metadata-Version: 2.4
Name: audittrail
Version: 1.0.1
Summary: Production-ready tamper-proof audit trail library with digital signatures, WORM protection, and compliance reporting for Python web frameworks.
Author-email: "Ethan P. Bonsall" <ethan.bonsall.dev@gmail.com>
License: MIT
Project-URL: Homepage, https://github.com/ethanbonsall/audittrail-py
Project-URL: Documentation, https://github.com/ethanbonsall/audittrail-py#readme
Project-URL: Repository, https://github.com/ethanbonsall/audittrail-py
Project-URL: Issues, https://github.com/ethanbonsall/audittrail-py/issues
Project-URL: Changelog, https://github.com/ethanbonsall/audittrail-py/blob/main/CHANGELOG.md
Keywords: audit,logging,compliance,security,tamper-proof,blockchain,WORM,signatures,SOX,HIPAA,PCI-DSS
Classifier: Development Status :: 5 - Production/Stable
Classifier: Intended Audience :: Developers
Classifier: Intended Audience :: Financial and Insurance Industry
Classifier: Intended Audience :: Healthcare Industry
Classifier: License :: OSI Approved :: MIT License
Classifier: Programming Language :: Python :: 3
Classifier: Programming Language :: Python :: 3.8
Classifier: Programming Language :: Python :: 3.9
Classifier: Programming Language :: Python :: 3.10
Classifier: Programming Language :: Python :: 3.11
Classifier: Programming Language :: Python :: 3.12
Classifier: Topic :: Security
Classifier: Topic :: System :: Logging
Classifier: Topic :: Software Development :: Libraries :: Python Modules
Requires-Python: >=3.8
License-File: LICENSE
Requires-Dist: click
Requires-Dist: fastapi
Requires-Dist: starlette
Requires-Dist: cryptography
Requires-Dist: tabulate
Dynamic: license-file
